prominence/__init__.py
prominence/artifact.py
prominence/auth.py
prominence/cli.py
prominence/client.py
prominence/dependency.py
prominence/exceptions.py
prominence/factory.py
prominence/inputfile.py
prominence/job.py
prominence/notification.py
prominence/policies.py
prominence/resources.py
prominence/task.py
prominence/workflow.py
prominence-0.20.2.data/scripts/prominence
prominence-0.20.2.dist-info/LICENSE
prominence-0.20.2.dist-info/METADATA
prominence-0.20.2.dist-info/WHEEL
prominence-0.20.2.dist-info/top_level.txt
prominence-0.20.2.dist-info/RECORD
