Metadata-Version: 2.1
Name: prominence
Version: 0.20.2
Summary: PROMINENCE CLI for managing batch jobs running across clouds
Home-page: https://prominence-eosc.github.io/docs
Author: Andrew Lahiff
Author-email: andrew.lahiff@ukaea.uk
Platform: any
License-File: LICENSE
Requires-Dist: requests
Requires-Dist: PyJWT
Requires-Dist: pyyaml
